{"alt forms":[],"term":"fe fato","slug":"fe_fato","search terms":{"glb":["fe fato","fe","fato"],"eng":["in fact","actually","de facto"],"epo":["fakte","efektive"],"spa":["de hecho","en realidad"]},"ipa":"fe \u02c8fato","ipa link":"http:\/\/ipa-reader.xyz\/?text=fe \u02c8fato&voice=Ewa","status":false,"category":"phrase","word class":"m","trans html":{"eng":"in fact, actually, de facto","epo":"fakte, efektive","spa":"de hecho, en realidad","deu":"","fra":"","rus":"","zho":""},"trans":{"eng":[["in fact","actually","de facto"]],"epo":[["fakte","efektive"]],"spa":[["de hecho","en realidad"]],"deu":[],"fra":[],"rus":[],"zho":[]},"etymology":{"derived":["fe",",","fato"],"derived trans":[{"slug":"fe","text":"fe","word class":"p","trans":{"eng":"at (<em>time<\/em>), at (<em>unspecified place<\/em>), in (<em>time<\/em>), for (<em>for the first time, etc.<\/em>), of (<em>relating to, number, quantity, amount<\/em>)","epo":"je, en (<em>tempo a\u016d loko<\/em>), por (<em>por la unua fojo, ktp<\/em>), da... (<em>Indikas rilaton kun la substantivo post \u011di. Simila al &ldquo;-li&rdquo; pri la substantivo anta\u016d \u011di.<\/em>)","spa":"en (<em>tiempo, lugar, estado<\/em>), a (<em>tiempo, modo<\/em>), por (<em>&ldquo;por primera vez&rdquo;, juramentos<\/em>), de (<em>relaci&oacute;n, tipo, n&uacute;mero, cantidad, objeto directo, modo, sustancia<\/em>), par, bajo, so, sobre (<em>aplicaci&oacute;n<\/em>)","deu":"","fra":"","rus":"","zho":""}},{"text":","},{"slug":"fato","text":"fato","word class":"b","trans":{"eng":"fact","epo":"fakto","spa":"hecho, dato","deu":"","fra":"","rus":"","zho":""}}]}}