{"alt forms":[],"term":"kopi","slug":"kopi","search terms":{"glb":["kopi"],"eng":["copy","duplicate"],"epo":["kopio","kopii"],"spa":["copia","copiar"]},"ipa":"\u02c8kopi","ipa link":"http:\/\/ipa-reader.xyz\/?text=\u02c8kopi&voice=Ewa","status":true,"category":"root","word class":"b.oj","trans html":{"eng":"copy, duplicate; copy, duplicate","epo":"kopio; kopii","spa":"copia; copiar","deu":"","fra":"","rus":"","zho":""},"trans":{"eng":[["copy","duplicate"],["copy","duplicate"]],"epo":[["kopio"],["kopii"]],"spa":[["copia"],["copiar"]],"deu":[],"fra":[],"rus":[],"zho":[]},"etymology":{"natlang":{"Doycisa":"Kopie","Englisa":"copy","Espanisa":"copia","Fransesa":"copie","Niponsa":"\u30b3\u30d4\u30fc &ldquo;kop\u012b&rdquo;","Parsisa":"\u06a9\u067e\u06cc &ldquo;kopi&rdquo;","Pilipinasa":"kopya","Putunhwa":"\u62f7\u8d1d &ldquo;k\u01ceob&egrave;i&rdquo;","Rusisa":"\u043a\u043e\u043f\u0438\u044f &ldquo;kopiya&rdquo;","Telugusa":"\u0c15\u0c3e\u0c2a\u0c40 &ldquo;k\u0101p\u012b&rdquo;","Turkisa":"kopya"}},"derived terms":{"exkopi":{"class":"b.oj","term":"exkopi","trans":{"eng":"copy out, upload","epo":"elkopio, al\u015duto; elkopii, al\u015duti","spa":"subida, carga; subir (<em>datos<\/em>), colgar","deu":"","fra":"","rus":"","zho":""}},"inkopi":{"class":"b.oj","term":"inkopi","trans":{"eng":"copy in, download","epo":"inkopio, el\u015duto; inkopii, el\u015duti","spa":"descarga, bajada; descargar (<em>datos<\/em>), bajar","deu":"","fra":"","rus":"","zho":""}},"kopido":{"class":"t","term":"kopido","trans":{"eng":"copied, duplicated","epo":"kopiita; kopiite","spa":"copiado, duplicado, replicado","deu":"","fra":"","rus":"","zho":""}},"kopihaki":{"class":"b.oj","term":"kopihaki","trans":{"eng":"copyright","epo":"kopirajto","spa":"derecho (de autor), <em>copyright<\/em>; registrar (los derechos de)","deu":"","fra":"","rus":"","zho":""}}},"rhyme":{"filipi":{"word class":"su n","term":"Filipi","eng":"Philippi","epo":"Filipio","spa":"Filipos","deu":"","fra":"","rus":"","zho":""},"hwepi":{"word class":"b.oj","term":"hwepi","eng":"avoidance, evasion; avoid, evade, dodge","epo":"evito; eviti","spa":"evitaci&oacute;n, evasi&oacute;n; evitar, evadir","deu":"","fra":"","rus":"","zho":""},"ityopi":{"word class":"su n","term":"Ityopi","eng":"Ethiopia","epo":"Etiopio, Etiopujo","spa":"Etiop&iacute;a","deu":"","fra":"","rus":"\u042d\u0444\u0438\u043e\u043f\u0438\u044f","zho":""},"kampi":{"word class":"b.nenoj","term":"kampi","eng":"camping; camp","epo":"kampado, bivako, tendumado; kampi, bivaki, tendumi","spa":"<em>camping<\/em>, acampada, campamento; acampar","deu":"","fra":"","rus":"","zho":""},"kapi":{"word class":"b","term":"kapi","eng":"head, top","epo":"kapo","spa":"cabeza, cima, parte de arriba","deu":"","fra":"","rus":"","zho":""},"kaspi":{"word class":"su n","term":"Kaspi","eng":"Caspian","epo":"Kaspio, Kaspia maro","spa":"Caspio (<em>lago<\/em>)","deu":"","fra":"","rus":"","zho":""},"marsupi":{"word class":"b","term":"marsupi","eng":"marsupium, pouch","epo":"marsupio","spa":"marsupio","deu":"","fra":"","rus":"","zho":""},"napi":{"word class":"b","term":"napi","eng":"diaper, nappy","epo":"vindotuko, vinda\u0135o, kalsonvinda\u0135o, vindo","spa":"pa&ntilde;al","deu":"","fra":"","rus":"","zho":""},"pipi":{"word class":"b.oj.ru","term":"pipi","eng":"piss, pee, wee","epo":"pisa\u0135o; pisi","spa":"orina (<em>no cl&iacute;nico<\/em>), pip&iacute;; hacer pip&iacute;","deu":"","fra":"","rus":"","zho":""},"popi":{"word class":"b","term":"popi","eng":"poppy, <em>Papaveraceae<\/em>","epo":"papavo, papavero","spa":"amapola, adormidera, <em>Papaveraceae<\/em>","deu":"","fra":"","rus":"","zho":""},"principi":{"word class":"b","term":"principi","eng":"principle","epo":"principo","spa":"principio, precepto","deu":"","fra":"","rus":"","zho":""},"terapi":{"word class":"b","term":"terapi","eng":"therapy, treatment; treat (with therapy)","epo":"terapio, kuracado; terapii","spa":"terapia, tratamiento; dar terapia","deu":"","fra":"","rus":"","zho":""},"topi":{"word class":"b","term":"topi","eng":"hat, cap","epo":"\u0109apelo","spa":"sombrero, tocado","deu":"","fra":"","rus":"","zho":""},"xupi":{"word class":"b","term":"xupi","eng":"bark (<em>tree<\/em>)","epo":"arbo\u015delo","spa":"corteza","deu":"","fra":"","rus":"","zho":""}},"rhyme exclusions":["kopi"]}