{"alt forms":[],"term":"papa ci","slug":"papa_ci","search terms":{"glb":["papa ci","papa","ci"],"eng":["daddy"],"epo":["pa\u0109jo"],"spa":["papi","papito"]},"ipa":"\u02c8papa t\u0361\u0283i","ipa link":"http:\/\/ipa-reader.xyz\/?text=\u02c8papa t\u0361\u0283i&voice=Ewa","status":false,"category":"phrase","word class":"b","trans html":{"eng":"daddy","epo":"pa\u0109jo","spa":"papi, papito","deu":"","fra":"","rus":"","zho":""},"trans":{"eng":[["daddy"]],"epo":[["pa\u0109jo"]],"spa":[["papi","papito"]],"deu":[],"fra":[],"rus":[],"zho":[]},"etymology":{"derived":["papa",",","ci"],"derived trans":[{"slug":"papa","text":"papa","word class":"b","trans":{"eng":"dad","epo":"pa\u0109jo","spa":"pap&aacute;","deu":"","fra":"","rus":"","zho":""}},{"text":","},{"slug":"ci","text":"ci","word class":"par","trans":{"eng":"denotes endearment or affection","epo":"-\u0109jo, -njo (por karese nomi)","spa":"-ito (<em>denota cari&ntilde;o o afecto<\/em>)","deu":"","fra":"","rus":"","zho":""}}]}}