{"alt forms":[],"term":"ultra-","slug":"ultra-","search terms":{"glb":["ultra-"],"eng":["super-","ultra-","beyond"],"epo":["preter-"],"spa":["ultra-","super-","supra-"]},"ipa":"ul\u02c8t\u027ea-","ipa link":"http:\/\/ipa-reader.xyz\/?text=ul\u02c8t\u027ea-&voice=Ewa","status":true,"category":"affix","word class":"lfik","trans html":{"eng":"super-, ultra-, beyond","epo":"preter-","spa":"ultra-, super-, supra-","deu":"","fra":"","rus":"","zho":""},"trans":{"eng":[["super-","ultra-","beyond"]],"epo":[["preter-"]],"spa":[["ultra-","super-","supra-"]],"deu":[],"fra":[],"rus":[],"zho":[]},"etymology":{"am oko":["ultra"]},"derived terms":{"ultrajiwa":{"class":"b.oj","term":"ultrajiwa","trans":{"eng":"survival; survive","epo":"pretervivo, travivo; pretervivi, travivi","spa":"supervivencia; sobrevivir","deu":"","fra":"","rus":"","zho":""}},"ultranaturali":{"class":"t","term":"ultranaturali","trans":{"eng":"supernatural; supernaturally","epo":"supernatura; supernature","spa":"sobrenatural","deu":"","fra":"","rus":"","zho":""}},"ultraordinari":{"class":"t","term":"ultraordinari","trans":{"eng":"extraordinary, exceptional","epo":"eksterordinara; eksterordinare","spa":"extraordinario, excepcional; extraordinariamente, excepcionalmente","deu":"","fra":"","rus":"","zho":""}},"ultrapasa":{"class":"b.oj","term":"ultrapasa","trans":{"eng":"pass by, surpass, exceed","epo":"preterpaso; preterpasi","spa":"superar","deu":"","fra":"","rus":"","zho":""}}},"rhyme exclusions":["ultra-"]}