{"ah":["a"],"amp\u00e8re":["amperi"],"anguille":["sarpenmahi"],"autisme":["awtiya"],"autiste":["awti","awtiyen"],"baguette":["gumbo"],"bel":["belu"],"blatte":["karoca"],"b\u00e2ton":["gumbo"],"cach\u00e9":["sangudo"],"cafard":["karoca"],"canada":["kanada"],"canadien":["kanadali","kanadayen"],"canadienne":["kanadali","kanadayen"],"candela":["kandela"],"canne":["gumbo"],"canneberge":["krenberi"],"catalyse":["katalisi"],"celsius":["selsyus"],"centim\u00e8tre":["centimetro"],"chandail":["sweter"],"cha\u00eene":["canal"],"coulomb":["kulom"],"croissant":["kruasan"],"croissant viennoiserie":["kruasan"],"d\u00e9cibel":["decibelu"],"farad":["faradi"],"gray":["grey"],"henry":["henri"],"hertz":["herzi"],"jeton":["token"],"joule":["jul"],"katal":["katalu"],"kebab":["kebabu"],"kelvin":["kelvin"],"lentille":["lense"],"lesotho":["lesutu"],"lumen":["lumen"],"lux":["lux"],"mole":["mol"],"mol\u00e9cule":["molekul"],"newton":["nyuton"],"oasis":["oasis"],"ohm":["om"],"ourdou":["urdu"],"pascal":["paskal"],"pharaon":["faraon"],"pieu":["gumbo"],"pixel":["piksel"],"pouvoir":["abil"],"po\u00eale":["tawa"],"po\u00eale cuisine":["tawa"],"pull-over":["sweter"],"quantum":["kwantum"],"radian":["radyan"],"rh\u00e9torique":["palalogi"],"service":["servi"],"servir":["servi"],"siemens":["simensu"],"sievert":["sivertu"],"soudainement":["abruto"],"statistique":["estatisti"],"s\u00e9rie":["serye"],"tesla":["tesla"],"trag\u00e9die":["tragedi"],"train":["tren"],"trauma":["trawma"],"traumatisme":["trawma"],"tricot":["sweter"],"trinidad":["trinidad"],"trinit\u00e9":["trinidad"],"trinit\u00e9 \u00eele":["trinidad"],"volt":["volti"],"watt":["wati"],"weber":["weber"],"\u00e9ther":["eter"]}